{
  "source_csv": "rho_sweep_m5_anchors.csv",
  "n_points": 51,
  "c_min": 1,
  "c_max": 169,
  "rho_min": 0.02857725078091,
  "rho_max": 0.963504413162,
  "rho_range": 0.93492716238109,
  "first_differences_sample": [
    [
      2,
      0.57839298813309
    ],
    [
      3,
      0.31925161587639994
    ],
    [
      4,
      0.03491981898320007
    ],
    [
      5,
      0.002258918006999955
    ],
    [
      24,
      0.0
    ],
    [
      25,
      0.0
    ],
    [
      26,
      0.0
    ],
    [
      27,
      0.0
    ],
    [
      46,
      0.0
    ],
    [
      47,
      0.0
    ],
    [
      48,
      0.0
    ],
    [
      49,
      0.0
    ],
    [
      55,
      0.0
    ],
    [
      56,
      0.0
    ],
    [
      57,
      0.0
    ],
    [
      58,
      0.0
    ],
    [
      68,
      0.0
    ],
    [
      69,
      0.0
    ],
    [
      70,
      0.0
    ],
    [
      71,
      0.0
    ]
  ],
  "first_differences_max_abs": 0.57839298813309,
  "first_differences_mean": 0.025967315027769167,
  "monotonicity": {
    "increases": 4,
    "decreases": 0,
    "flats": 32,
    "decrease_events": [],
    "num_decrease_events": 0
  },
  "autocorrelation_lag1_10": {
    "1": 0.35377557024847806,
    "2": 0.03581311398041862,
    "3": 0.00015111447814933492,
    "4": -0.0029496677090352927,
    "5": -0.003902346252729371,
    "6": -0.004786878070780888,
    "7": -0.005711615879909015,
    "8": -0.006679364749926825,
    "9": -0.00769319689946929,
    "10": -0.008756484275818705
  },
  "autocorrelation_at_22_53_75": {
    "22": -0.02723568557513268
  },
  "mod22_group_stats": {
    "0": {
      "n": 2,
      "mean": 0.963504413162,
      "var": 0.0,
      "min": 0.963504413162,
      "max": 0.963504413162
    },
    "1": {
      "n": 6,
      "mean": 0.8076832194318183,
      "var": 0.12140122207749403,
      "min": 0.02857725078091,
      "max": 0.963504413162
    },
    "2": {
      "n": 4,
      "mean": 0.8743708696,
      "var": 0.023834365763756846,
      "min": 0.606970238914,
      "max": 0.963504413162
    },
    "3": {
      "n": 4,
      "mean": 0.9541837735691,
      "var": 0.00026062296726220513,
      "min": 0.9262218547904,
      "max": 0.963504413162
    },
    "4": {
      "n": 4,
      "mean": 0.9629137283149,
      "var": 1.0467257657805856e-06,
      "min": 0.9611416737736,
      "max": 0.963504413162
    },
    "5": {
      "n": 4,
      "mean": 0.96347845781665,
      "var": 2.0210398567121747e-09,
      "min": 0.9634005917806,
      "max": 0.963504413162
    },
    "6": {
      "n": 2,
      "mean": 0.963504413162,
      "var": 0.0,
      "min": 0.963504413162,
      "max": 0.963504413162
    },
    "7": {
      "n": 1,
      "mean": 0.963504413162,
      "var": 0.0,
      "min": 0.963504413162,
      "max": 0.963504413162
    },
    "8": {
      "n": 1,
      "mean": 0.963504413162,
      "var": 0.0,
      "min": 0.963504413162,
      "max": 0.963504413162
    },
    "9": {
      "n": 1,
      "mean": 0.963504413162,
      "var": 0.0,
      "min": 0.963504413162,
      "max": 0.963504413162
    },
    "10": {
      "n": 5,
      "mean": 0.96350441316188,
      "var": 5.75931890158499e-26,
      "min": 0.9635044131614,
      "max": 0.963504413162
    },
    "11": {
      "n": 2,
      "mean": 0.963504413162,
      "var": 0.0,
      "min": 0.963504413162,
      "max": 0.963504413162
    },
    "12": {
      "n": 2,
      "mean": 0.963504413162,
      "var": 0.0,
      "min": 0.963504413162,
      "max": 0.963504413162
    },
    "13": {
      "n": 2,
      "mean": 0.963504413162,
      "var": 0.0,
      "min": 0.963504413162,
      "max": 0.963504413162
    },
    "14": {
      "n": 2,
      "mean": 0.963504413162,
      "var": 0.0,
      "min": 0.963504413162,
      "max": 0.963504413162
    },
    "15": {
      "n": 1,
      "mean": 0.963504413162,
      "var": 0.0,
      "min": 0.963504413162,
      "max": 0.963504413162
    },
    "19": {
      "n": 4,
      "mean": 0.963504413162,
      "var": 0.0,
      "min": 0.963504413162,
      "max": 0.963504413162
    },
    "20": {
      "n": 2,
      "mean": 0.963504413162,
      "var": 0.0,
      "min": 0.963504413162,
      "max": 0.963504413162
    },
    "21": {
      "n": 2,
      "mean": 0.963504413162,
      "var": 0.0,
      "min": 0.963504413162,
      "max": 0.963504413162
    }
  },
  "mod53_group_stats": {
    "1": {
      "n": 4,
      "mean": 0.7297726225667275,
      "var": 0.16389164980461693,
      "min": 0.02857725078091,
      "max": 0.963504413162
    },
    "2": {
      "n": 4,
      "mean": 0.8743708696,
      "var": 0.023834365763756846,
      "min": 0.606970238914,
      "max": 0.963504413162
    },
    "3": {
      "n": 4,
      "mean": 0.9541837735691,
      "var": 0.00026062296726220513,
      "min": 0.9262218547904,
      "max": 0.963504413162
    },
    "4": {
      "n": 4,
      "mean": 0.9629137283149,
      "var": 1.0467257657805856e-06,
      "min": 0.9611416737736,
      "max": 0.963504413162
    },
    "5": {
      "n": 4,
      "mean": 0.96347845781665,
      "var": 2.0210398567121747e-09,
      "min": 0.9634005917806,
      "max": 0.963504413162
    },
    "10": {
      "n": 4,
      "mean": 0.96350441316185,
      "var": 6.749201780017012e-26,
      "min": 0.9635044131614,
      "max": 0.963504413162
    },
    "14": {
      "n": 1,
      "mean": 0.963504413162,
      "var": 0.0,
      "min": 0.963504413162,
      "max": 0.963504413162
    },
    "15": {
      "n": 1,
      "mean": 0.963504413162,
      "var": 0.0,
      "min": 0.963504413162,
      "max": 0.963504413162
    },
    "16": {
      "n": 1,
      "mean": 0.963504413162,
      "var": 0.0,
      "min": 0.963504413162,
      "max": 0.963504413162
    },
    "17": {
      "n": 1,
      "mean": 0.963504413162,
      "var": 0.0,
      "min": 0.963504413162,
      "max": 0.963504413162
    },
    "18": {
      "n": 1,
      "mean": 0.963504413162,
      "var": 0.0,
      "min": 0.963504413162,
      "max": 0.963504413162
    },
    "23": {
      "n": 2,
      "mean": 0.963504413162,
      "var": 0.0,
      "min": 0.963504413162,
      "max": 0.963504413162
    },
    "24": {
      "n": 2,
      "mean": 0.963504413162,
      "var": 0.0,
      "min": 0.963504413162,
      "max": 0.963504413162
    },
    "25": {
      "n": 2,
      "mean": 0.963504413162,
      "var": 0.0,
      "min": 0.963504413162,
      "max": 0.963504413162
    },
    "26": {
      "n": 2,
      "mean": 0.963504413162,
      "var": 0.0,
      "min": 0.963504413162,
      "max": 0.963504413162
    },
    "27": {
      "n": 2,
      "mean": 0.963504413162,
      "var": 0.0,
      "min": 0.963504413162,
      "max": 0.963504413162
    },
    "32": {
      "n": 2,
      "mean": 0.963504413162,
      "var": 0.0,
      "min": 0.963504413162,
      "max": 0.963504413162
    },
    "45": {
      "n": 2,
      "mean": 0.963504413162,
      "var": 0.0,
      "min": 0.963504413162,
      "max": 0.963504413162
    },
    "46": {
      "n": 2,
      "mean": 0.963504413162,
      "var": 0.0,
      "min": 0.963504413162,
      "max": 0.963504413162
    },
    "47": {
      "n": 2,
      "mean": 0.963504413162,
      "var": 0.0,
      "min": 0.963504413162,
      "max": 0.963504413162
    },
    "48": {
      "n": 2,
      "mean": 0.963504413162,
      "var": 0.0,
      "min": 0.963504413162,
      "max": 0.963504413162
    },
    "49": {
      "n": 2,
      "mean": 0.963504413162,
      "var": 0.0,
      "min": 0.963504413162,
      "max": 0.963504413162
    }
  },
  "mod75_group_stats": {
    "1": {
      "n": 3,
      "mean": 0.6518620257016366,
      "var": 0.19424195532399044,
      "min": 0.02857725078091,
      "max": 0.963504413162
    },
    "2": {
      "n": 3,
      "mean": 0.8446596884126666,
      "var": 0.028248137201489595,
      "min": 0.606970238914,
      "max": 0.963504413162
    },
    "3": {
      "n": 3,
      "mean": 0.9510768937048,
      "var": 0.0003088864797181691,
      "min": 0.9262218547904,
      "max": 0.963504413162
    },
    "4": {
      "n": 3,
      "mean": 0.9627168333658668,
      "var": 1.2405638705547679e-06,
      "min": 0.9611416737736,
      "max": 0.963504413162
    },
    "5": {
      "n": 3,
      "mean": 0.9634698060348666,
      "var": 2.395306496844059e-09,
      "min": 0.9634005917806,
      "max": 0.963504413162
    },
    "10": {
      "n": 3,
      "mean": 0.9635044131617999,
      "var": 7.999054509321717e-26,
      "min": 0.9635044131614,
      "max": 0.963504413162
    },
    "11": {
      "n": 1,
      "mean": 0.963504413162,
      "var": 0.0,
      "min": 0.963504413162,
      "max": 0.963504413162
    },
    "12": {
      "n": 1,
      "mean": 0.963504413162,
      "var": 0.0,
      "min": 0.963504413162,
      "max": 0.963504413162
    },
    "13": {
      "n": 1,
      "mean": 0.963504413162,
      "var": 0.0,
      "min": 0.963504413162,
      "max": 0.963504413162
    },
    "14": {
      "n": 1,
      "mean": 0.963504413162,
      "var": 0.0,
      "min": 0.963504413162,
      "max": 0.963504413162
    },
    "19": {
      "n": 1,
      "mean": 0.963504413162,
      "var": 0.0,
      "min": 0.963504413162,
      "max": 0.963504413162
    },
    "23": {
      "n": 1,
      "mean": 0.963504413162,
      "var": 0.0,
      "min": 0.963504413162,
      "max": 0.963504413162
    },
    "24": {
      "n": 1,
      "mean": 0.963504413162,
      "var": 0.0,
      "min": 0.963504413162,
      "max": 0.963504413162
    },
    "25": {
      "n": 1,
      "mean": 0.963504413162,
      "var": 0.0,
      "min": 0.963504413162,
      "max": 0.963504413162
    },
    "26": {
      "n": 1,
      "mean": 0.963504413162,
      "var": 0.0,
      "min": 0.963504413162,
      "max": 0.963504413162
    },
    "27": {
      "n": 1,
      "mean": 0.963504413162,
      "var": 0.0,
      "min": 0.963504413162,
      "max": 0.963504413162
    },
    "32": {
      "n": 2,
      "mean": 0.963504413162,
      "var": 0.0,
      "min": 0.963504413162,
      "max": 0.963504413162
    },
    "33": {
      "n": 1,
      "mean": 0.963504413162,
      "var": 0.0,
      "min": 0.963504413162,
      "max": 0.963504413162
    },
    "34": {
      "n": 1,
      "mean": 0.963504413162,
      "var": 0.0,
      "min": 0.963504413162,
      "max": 0.963504413162
    },
    "35": {
      "n": 1,
      "mean": 0.963504413162,
      "var": 0.0,
      "min": 0.963504413162,
      "max": 0.963504413162
    },
    "36": {
      "n": 1,
      "mean": 0.963504413162,
      "var": 0.0,
      "min": 0.963504413162,
      "max": 0.963504413162
    },
    "41": {
      "n": 1,
      "mean": 0.963504413162,
      "var": 0.0,
      "min": 0.963504413162,
      "max": 0.963504413162
    },
    "45": {
      "n": 1,
      "mean": 0.963504413162,
      "var": 0.0,
      "min": 0.963504413162,
      "max": 0.963504413162
    },
    "46": {
      "n": 1,
      "mean": 0.963504413162,
      "var": 0.0,
      "min": 0.963504413162,
      "max": 0.963504413162
    },
    "47": {
      "n": 1,
      "mean": 0.963504413162,
      "var": 0.0,
      "min": 0.963504413162,
      "max": 0.963504413162
    },
    "48": {
      "n": 1,
      "mean": 0.963504413162,
      "var": 0.0,
      "min": 0.963504413162,
      "max": 0.963504413162
    },
    "49": {
      "n": 1,
      "mean": 0.963504413162,
      "var": 0.0,
      "min": 0.963504413162,
      "max": 0.963504413162
    },
    "54": {
      "n": 1,
      "mean": 0.963504413162,
      "var": 0.0,
      "min": 0.963504413162,
      "max": 0.963504413162
    },
    "55": {
      "n": 1,
      "mean": 0.963504413162,
      "var": 0.0,
      "min": 0.963504413162,
      "max": 0.963504413162
    },
    "56": {
      "n": 1,
      "mean": 0.963504413162,
      "var": 0.0,
      "min": 0.963504413162,
      "max": 0.963504413162
    },
    "57": {
      "n": 1,
      "mean": 0.963504413162,
      "var": 0.0,
      "min": 0.963504413162,
      "max": 0.963504413162
    },
    "58": {
      "n": 1,
      "mean": 0.963504413162,
      "var": 0.0,
      "min": 0.963504413162,
      "max": 0.963504413162
    },
    "63": {
      "n": 1,
      "mean": 0.963504413162,
      "var": 0.0,
      "min": 0.963504413162,
      "max": 0.963504413162
    },
    "67": {
      "n": 1,
      "mean": 0.963504413162,
      "var": 0.0,
      "min": 0.963504413162,
      "max": 0.963504413162
    },
    "68": {
      "n": 1,
      "mean": 0.963504413162,
      "var": 0.0,
      "min": 0.963504413162,
      "max": 0.963504413162
    },
    "69": {
      "n": 1,
      "mean": 0.963504413162,
      "var": 0.0,
      "min": 0.963504413162,
      "max": 0.963504413162
    },
    "70": {
      "n": 1,
      "mean": 0.963504413162,
      "var": 0.0,
      "min": 0.963504413162,
      "max": 0.963504413162
    },
    "71": {
      "n": 1,
      "mean": 0.963504413162,
      "var": 0.0,
      "min": 0.963504413162,
      "max": 0.963504413162
    }
  },
  "lag_alignment_tests": {
    "22": {
      "lag": 22,
      "n_pairs": 24,
      "mean_abs_diff": 0.055467102323795404,
      "max_abs_diff": 0.93492716238109,
      "exact_matches_lt_1e-9": 19,
      "sample_first5": [
        [
          1,
          0.02857725078091,
          0.963504413162,
          0.93492716238109
        ],
        [
          2,
          0.606970238914,
          0.963504413162,
          0.35653417424799994
        ],
        [
          3,
          0.9262218547904,
          0.963504413162,
          0.037282558371599994
        ],
        [
          4,
          0.9611416737736,
          0.963504413162,
          0.002362739388399926
        ],
        [
          5,
          0.9634005917806,
          0.963504413162,
          0.0001038213813999711
        ]
      ]
    },
    "53": {
      "lag": 53,
      "n_pairs": 24,
      "mean_abs_diff": 0.055467102323795404,
      "max_abs_diff": 0.93492716238109,
      "exact_matches_lt_1e-9": 19,
      "sample_first5": [
        [
          1,
          0.02857725078091,
          0.963504413162,
          0.93492716238109
        ],
        [
          2,
          0.606970238914,
          0.963504413162,
          0.35653417424799994
        ],
        [
          3,
          0.9262218547904,
          0.963504413162,
          0.037282558371599994
        ],
        [
          4,
          0.9611416737736,
          0.963504413162,
          0.002362739388399926
        ],
        [
          5,
          0.9634005917806,
          0.963504413162,
          0.0001038213813999711
        ]
      ]
    },
    "75": {
      "lag": 75,
      "n_pairs": 13,
      "mean_abs_diff": 0.10240080429008383,
      "max_abs_diff": 0.93492716238109,
      "exact_matches_lt_1e-9": 8,
      "sample_first5": [
        [
          1,
          0.02857725078091,
          0.963504413162,
          0.93492716238109
        ],
        [
          2,
          0.606970238914,
          0.963504413162,
          0.35653417424799994
        ],
        [
          3,
          0.9262218547904,
          0.963504413162,
          0.037282558371599994
        ],
        [
          4,
          0.9611416737736,
          0.963504413162,
          0.002362739388399926
        ],
        [
          5,
          0.9634005917806,
          0.963504413162,
          0.0001038213813999711
        ]
      ]
    }
  },
  "interpretation_note": "If rho(C) converges to (or is already at) a constant for the C range covered, first differences ~0, autocorrelation undefined/degenerate (zero variance), and lag tests will trivially show near-zero diffs everywhere -- this indicates rho is C-INDEPENDENT in this regime, not that it has periodic structure at these specific lags. Only a nonzero-variance regime (e.g. small-C transient) can distinguish genuine 22/53/75 alignment from generic convergence."
}